pillarsdk/__init__.py
pillarsdk/activities.py
pillarsdk/api.py
pillarsdk/binary_files.py
pillarsdk/config.py
pillarsdk/exceptions.py
pillarsdk/files.py
pillarsdk/groups.py
pillarsdk/nodes.py
pillarsdk/organizations.py
pillarsdk/projects.py
pillarsdk/resource.py
pillarsdk/tokens.py
pillarsdk/users.py
pillarsdk/utils.py
pillarsdk-1.10.dist-info/LICENSE.md
pillarsdk-1.10.dist-info/WHEEL
pillarsdk-1.10.dist-info/METADATA
pillarsdk-1.10.dist-info/RECORD
