Metadata-Version: 2.1
Name: pillarsdk
Version: 1.10
Summary: The Pillar REST SDK provides Python APIs to communicate to the Pillar webservices.
Author: Francesco Siddi
Author-email: francesco@blender.org
Requires-Python: >=3.5,<4.0
Classifier: Intended Audience :: Developers
Classifier: Operating System :: OS Independent
Classifier: Programming Language :: Python
Classifier: Programming Language :: Python :: 3
Classifier: Programming Language :: Python :: 3.5
Classifier: Programming Language :: Python :: 3.6
Classifier: Programming Language :: Python :: 3.7
Classifier: Topic :: Software Development :: Libraries :: Python Modules
Requires-Dist: pyOpenSSL (>=19,<20)
Requires-Dist: requests (>=2,<3)
